ejabberdapi/Ejabberdapi.py
ejabberdapi/__init__.py
EjabberdAPI-0.1.7.1.dist-info/LICENSE
EjabberdAPI-0.1.7.1.dist-info/METADATA
EjabberdAPI-0.1.7.1.dist-info/WHEEL
EjabberdAPI-0.1.7.1.dist-info/top_level.txt
EjabberdAPI-0.1.7.1.dist-info/RECORD
