Metadata-Version: 2.1
Name: EjabberdAPI
Version: 0.1.7.1
Summary: Python wrapper for Ejabberd API.
Home-page: https://git.mastodont.cat/spla/EjabberdAPI.py
Author: spla
Author-email: llemena_obrer.0u@icloud.com
Project-URL: Bug Tracker, https://git.mastodont.cat/spla/EjabberdAPI.py/issues
Keywords: ejabberd xmpp chat omemo
Classifier: License :: OSI Approved :: GNU General Public License v3 (GPLv3)
Classifier: Topic :: Software Development :: Libraries :: Python Modules
Classifier: Topic :: Communications
Classifier: Intended Audience :: Developers
Classifier: Topic :: Internet :: XMPP
Classifier: Programming Language :: Python :: 3
Requires-Python: >=3.8
License-File: LICENSE
Requires-Dist: requests
